nilm_usb/NILM.py
nilm_usb/__init__.py
nilm_usb-0.0.3.dist-info/METADATA
nilm_usb-0.0.3.dist-info/WHEEL
nilm_usb-0.0.3.dist-info/licenses/LICENSE
nilm_usb-0.0.3.dist-info/RECORD
