Metadata-Version: 2.3
Name: nilm_usb
Version: 0.0.3
Summary: A NILM images classifier
Project-URL: Homepage, https://github.com/ufotechco/nilm_usb
Author-email: UFOTECH <gerencia@ufotech.co>, Silvia Moreno <silvia.moreno@unisimon.edu.co>
License-File: LICENSE
Classifier: License :: OSI Approved :: MIT License
Classifier: Operating System :: OS Independent
Classifier: Programming Language :: Python :: 3
Requires-Python: >=3.10
Requires-Dist: keras==3.2.0
Requires-Dist: opencv-python>=4.9
Requires-Dist: scikit-learn>=1.4
Requires-Dist: scipy==1.13.0
Requires-Dist: tensorflow==2.16.1
